jinjaapidoc/__init__.py
jinjaapidoc/ext.py
jinjaapidoc/gendoc.py
jinjaapidoc/autosummarytemplates/autosummary/class.rst
jinjaapidoc/templates/jinjaapi_module.rst
jinjaapidoc/templates/jinjaapi_package.rst
jinjaapidoc-0.5.0.dist-info/AUTHORS.rst
jinjaapidoc-0.5.0.dist-info/LICENSE
jinjaapidoc-0.5.0.dist-info/METADATA
jinjaapidoc-0.5.0.dist-info/WHEEL
jinjaapidoc-0.5.0.dist-info/entry_points.txt
jinjaapidoc-0.5.0.dist-info/top_level.txt
jinjaapidoc-0.5.0.dist-info/RECORD
