Metadata-Version: 2.1
Name: jinjaapidoc
Version: 0.5.0
Summary: Sphinx API Doc with Jinja2 templates
Home-page: https://github.com/storax/jinjaapidoc
Author: David Zuber
Author-email: zuber.david@gmx.de
License: BSD
Keywords: jinjaapidoc
Platform: UNKNOWN
Classifier: Development Status :: 3 - Alpha
Classifier: Intended Audience :: Developers
Classifier: License :: OSI Approved :: BSD License
Classifier: Natural Language :: English
Classifier: Programming Language :: Python :: 3
Classifier: Programming Language :: Python :: 3.6
Classifier: Topic :: Documentation :: Sphinx
Classifier: Framework :: Sphinx :: Extension
Requires-Dist: jinja2
Requires-Dist: sphinx (>=1.8.5)
